{
 "time": 1522595107332,
 "lists": [
  {
   "id": 936740229163208700,
   "id_str": "936740229163208704",
   "created_at": "Fri Dec 01 23:34:09 +0000 2017",
   "text": "RT @OSS_Paris: #OSSPARIS17 arrive ! Demandez votre badge pour l'événement #opensource de l'année → https://t.co/KMVwq2RgNp https://t.co/xEl…",
   "retweet_count": 36,
   "favorite_count": 0,
   "place": null,
   "in_reply_to_status_id": null,
   "in_reply_to_status_id_str": null,
   "in_reply_to_screen_name": null,
   "urls": [
    {
     "url": "https://t.co/KMVwq2RgNp",
     "expand": "http://bit.ly/OSSPARIS17"
    }
   ],
   "retweeted_status": {
    "id": 910149826213539800,
    "id_str": "910149826213539841",
    "created_at": "Tue Sep 19 14:33:22 +0000 2017",
    "text": "#OSSPARIS17 arrive ! Demandez votre badge pour l'événement #opensource de l'année → https://t.co/KMVwq2RgNp https://t.co/xEl8w6nrfb",
    "retweet_count": 36,
    "favorite_count": 30,
    "place": null,
    "in_reply_to_status_id": null,
    "in_reply_to_status_id_str": null,
    "in_reply_to_screen_name": null,
    "urls": [
     {
      "url": "https://t.co/KMVwq2RgNp",
      "expand": "http://bit.ly/OSSPARIS17"
     }
    ]
   }
  }
 ]
}